<?xml version="1.0" encoding="utf-8"?>
<clothing-items>
 <clothing>
  <id>
   121421889
  </id>
  <name>
   Fila Umbrellas E-5321
  </name>
  <category>
   Umbrellas
  </category>
  <size>
   XL
  </size>
  <color>
   Желтый
  </color>
  <material>
   Хлопок
  </material>
  <price>
   682746
  </price>
  <rating>
   1.94
  </rating>
  <reviews>
   660877
  </reviews>
  <new>
   -
  </new>
  <exclusive>
   no
  </exclusive>
  <sporty>
   no
  </sporty>
 </clothing>
 <clothing>
  <id>
   664019216
  </id>
  <name>
   Fila Belts L-3362
  </name>
  <category>
   Belts
  </category>
  <size>
   XL
  </size>
  <color>
   Красный
  </color>
  <material>
   Вискоза
  </material>
  <price>
   952885
  </price>
  <rating>
   1.88
  </rating>
  <reviews>
   543869
  </reviews>
  <new>
   -
  </new>
  <sporty>
   no
  </sporty>
 </clothing>
 <clothing>
  <id>
   570328161
  </id>
  <name>
   Nike Shoes D-6803
  </name>
  <category>
   Shoes
  </category>
  <size>
   M
  </size>
  <color>
   Синий
  </color>
  <material>
   Вискоза
  </material>
  <price>
   872938
  </price>
  <rating>
   4.63
  </rating>
  <reviews>
   756289
  </reviews>
  <new>
   -
  </new>
  <sporty>
   yes
  </sporty>
 </clothing>
 <clothing>
  <id>
   625211591
  </id>
  <name>
   Adidas Umbrellas T-7461
  </name>
  <category>
   Umbrellas
  </category>
  <size>
   XXL
  </size>
  <color>
   Красный
  </color>
  <material>
   Нейлон
  </material>
  <price>
   239375
  </price>
  <rating>
   3.92
  </rating>
  <reviews>
   622276
  </reviews>
  <exclusive>
   no
  </exclusive>
  <sporty>
   yes
  </sporty>
 </clothing>
 <clothing>
  <id>
   974222982
  </id>
  <name>
   Under Armour Hat W-4771
  </name>
  <category>
   Hat
  </category>
  <size>
   XXL
  </size>
  <color>
   Голубой
  </color>
  <material>
   Вискоза
  </material>
  <price>
   803884
  </price>
  <rating>
   2.55
  </rating>
  <reviews>
   976210
  </reviews>
  <sporty>
   no
  </sporty>
 </clothing>
 <clothing>
  <id>
   541783656
  </id>
  <name>
   Under Armour Shirt S-2233
  </name>
  <category>
   Shirt
  </category>
  <size>
   S
  </size>
  <color>
   Оранжевый
  </color>
  <material>
   Кожа
  </material>
  <price>
   777828
  </price>
  <rating>
   2.53
  </rating>
  <reviews>
   544315
  </reviews>
  <exclusive>
   no
  </exclusive>
 </clothing>
 <clothing>
  <id>
   721540179
  </id>
  <name>
   Puma Shirt N-6466
  </name>
  <category>
   Shirt
  </category>
  <size>
   S
  </size>
  <color>
   Желтый
  </color>
  <material>
   Кожа
  </material>
  <price>
   921802
  </price>
  <rating>
   1.26
  </rating>
  <reviews>
   412633
  </reviews>
  <new>
   +
  </new>
  <exclusive>
   no
  </exclusive>
 </clothing>
 <clothing>
  <id>
   613092715
  </id>
  <name>
   Vans Gloves G-6551
  </name>
  <category>
   Gloves
  </category>
  <size>
   L
  </size>
  <color>
   Голубой
  </color>
  <material>
   Нейлон
  </material>
  <price>
   525886
  </price>
  <rating>
   4.79
  </rating>
  <reviews>
   725566
  </reviews>
 </clothing>
 <clothing>
  <id>
   472006977
  </id>
  <name>
   Lacoste Dress D-6619
  </name>
  <category>
   Dress
  </category>
  <size>
   XXL
  </size>
  <color>
   Голубой
  </color>
  <material>
   Хлопок
  </material>
  <price>
   971097
  </price>
  <rating>
   3.6
  </rating>
  <reviews>
   100255
  </reviews>
  <new>
   +
  </new>
 </clothing>
 <clothing>
  <id>
   856467415
  </id>
  <name>
   Adidas Blouse O-9145
  </name>
  <category>
   Blouse
  </category>
  <size>
   XXL
  </size>
  <color>
   Желтый
  </color>
  <material>
   Шерсть
  </material>
  <price>
   372041
  </price>
  <rating>
   1.57
  </rating>
  <reviews>
   705902
  </reviews>
  <new>
   +
  </new>
  <exclusive>
   yes
  </exclusive>
  <sporty>
   no
  </sporty>
 </clothing>
 <clothing>
  <id>
   178818943
  </id>
  <name>
   DC Jacket Z-9441
  </name>
  <category>
   Jacket
  </category>
  <size>
   XXL
  </size>
  <color>
   Голубой
  </color>
  <material>
   Вискоза
  </material>
  <price>
   478213
  </price>
  <rating>
   3.24
  </rating>
  <reviews>
   60188
  </reviews>
  <new>
   -
  </new>
  <sporty>
   no
  </sporty>
 </clothing>
 <clothing>
  <id>
   953126834
  </id>
  <name>
   Converse Socks R-2591
  </name>
  <category>
   Socks
  </category>
  <size>
   L
  </size>
  <color>
   Желтый
  </color>
  <material>
   Лен
  </material>
  <price>
   556501
  </price>
  <rating>
   3.93
  </rating>
  <reviews>
   269075
  </reviews>
  <new>
   +
  </new>
  <exclusive>
   yes
  </exclusive>
 </clothing>
 <clothing>
  <id>
   461279758
  </id>
  <name>
   Lacoste Jeans A-1128
  </name>
  <category>
   Jeans
  </category>
  <size>
   S
  </size>
  <color>
   Зеленый
  </color>
  <material>
   Шерсть
  </material>
  <price>
   100857
  </price>
  <rating>
   1.08
  </rating>
  <reviews>
   166949
  </reviews>
  <exclusive>
   no
  </exclusive>
 </clothing>
 <clothing>
  <id>
   100015670
  </id>
  <name>
   Nike Pants N-5908
  </name>
  <category>
   Pants
  </category>
  <size>
   L
  </size>
  <color>
   Оранжевый
  </color>
  <material>
   Нейлон
  </material>
  <price>
   543062
  </price>
  <rating>
   2.79
  </rating>
  <reviews>
   408112
  </reviews>
  <new>
   -
  </new>
  <exclusive>
   no
  </exclusive>
  <sporty>
   yes
  </sporty>
 </clothing>
 <clothing>
  <id>
   566447033
  </id>
  <name>
   Under Armour Sweater U-3875
  </name>
  <category>
   Sweater
  </category>
  <size>
   M
  </size>
  <color>
   Желтый
  </color>
  <material>
   Шерсть
  </material>
  <price>
   395605
  </price>
  <rating>
   3.61
  </rating>
  <reviews>
   706537
  </reviews>
  <new>
   +
  </new>
  <sporty>
   yes
  </sporty>
 </clothing>
 <clothing>
  <id>
   554540493
  </id>
  <name>
   New Balance Shirt A-2961
  </name>
  <category>
   Shirt
  </category>
  <size>
   M
  </size>
  <color>
   Голубой
  </color>
  <material>
   Нейлон
  </material>
  <price>
   407617
  </price>
  <rating>
   4.83
  </rating>
  <reviews>
   411426
  </reviews>
  <new>
   -
  </new>
  <sporty>
   yes
  </sporty>
 </clothing>
 <clothing>
  <id>
   944959906
  </id>
  <name>
   Nike Belts A-3362
  </name>
  <category>
   Belts
  </category>
  <size>
   S
  </size>
  <color>
   Зеленый
  </color>
  <material>
   Полиэстер
  </material>
  <price>
   367463
  </price>
  <rating>
   2.22
  </rating>
  <reviews>
   739741
  </reviews>
  <exclusive>
   yes
  </exclusive>
  <sporty>
   yes
  </sporty>
 </clothing>
 <clothing>
  <id>
   646978159
  </id>
  <name>
   Under Armour Umbrellas E-6505
  </name>
  <category>
   Umbrellas
  </category>
  <size>
   M
  </size>
  <color>
   Синий
  </color>
  <material>
   Кожа
  </material>
  <price>
   153721
  </price>
  <rating>
   2.27
  </rating>
  <reviews>
   364896
  </reviews>
  <new>
   -
  </new>
  <exclusive>
   yes
  </exclusive>
  <sporty>
   yes
  </sporty>
 </clothing>
 <clothing>
  <id>
   268786899
  </id>
  <name>
   Reebok Sweater L-3014
  </name>
  <category>
   Sweater
  </category>
  <size>
   S
  </size>
  <color>
   Голубой
  </color>
  <material>
   Хлопок
  </material>
  <price>
   313595
  </price>
  <rating>
   4.46
  </rating>
  <reviews>
   713340
  </reviews>
  <new>
   -
  </new>
  <sporty>
   yes
  </sporty>
 </clothing>
 <clothing>
  <id>
   836044795
  </id>
  <name>
   Addidas Jeans A-6888
  </name>
  <category>
   Jeans
  </category>
  <size>
   S
  </size>
  <color>
   Фиолетовый
  </color>
  <material>
   Нейлон
  </material>
  <price>
   969145
  </price>
  <rating>
   4.91
  </rating>
  <reviews>
   631522
  </reviews>
  <new>
   -
  </new>
  <sporty>
   no
  </sporty>
 </clothing>
 <clothing>
  <id>
   778605774
  </id>
  <name>
   Vans Socks N-3375
  </name>
  <category>
   Socks
  </category>
  <size>
   XXL
  </size>
  <color>
   Оранжевый
  </color>
  <material>
   Нейлон
  </material>
  <price>
   225634
  </price>
  <rating>
   2.43
  </rating>
  <reviews>
   242684
  </reviews>
  <exclusive>
   no
  </exclusive>
  <sporty>
   no
  </sporty>
 </clothing>
 <clothing>
  <id>
   787006372
  </id>
  <name>
   DC Blouse H-8905
  </name>
  <category>
   Blouse
  </category>
  <size>
   L
  </size>
  <color>
   Оранжевый
  </color>
  <material>
   Полиэстер
  </material>
  <price>
   275343
  </price>
  <rating>
   3.86
  </rating>
  <reviews>
   631213
  </reviews>
  <new>
   +
  </new>
  <exclusive>
   no
  </exclusive>
  <sporty>
   no
  </sporty>
 </clothing>
 <clothing>
  <id>
   232940875
  </id>
  <name>
   Reebok Gloves A-6687
  </name>
  <category>
   Gloves
  </category>
  <size>
   XL
  </size>
  <color>
   Фиолетовый
  </color>
  <material>
   Шелк
  </material>
  <price>
   235626
  </price>
  <rating>
   3.53
  </rating>
  <reviews>
   50819
  </reviews>
  <exclusive>
   yes
  </exclusive>
 </clothing>
 <clothing>
  <id>
   474952841
  </id>
  <name>
   Asics T-shirt J-2171
  </name>
  <category>
   T-shirt
  </category>
  <size>
   L
  </size>
  <color>
   Синий
  </color>
  <material>
   Шелк
  </material>
  <price>
   378555
  </price>
  <rating>
   1.22
  </rating>
  <reviews>
   39617
  </reviews>
  <sporty>
   no
  </sporty>
 </clothing>
 <clothing>
  <id>
   275891686
  </id>
  <name>
   Ellesse Shirt V-5367
  </name>
  <category>
   Shirt
  </category>
  <size>
   XXL
  </size>
  <color>
   Желтый
  </color>
  <material>
   Шелк
  </material>
  <price>
   204694
  </price>
  <rating>
   1.6
  </rating>
  <reviews>
   283330
  </reviews>
  <new>
   -
  </new>
  <exclusive>
   no
  </exclusive>
 </clothing>
 <clothing>
  <id>
   965368773
  </id>
  <name>
   Brooks Hat M-4008
  </name>
  <category>
   Hat
  </category>
  <size>
   S
  </size>
  <color>
   Красный
  </color>
  <material>
   Полиэстер
  </material>
  <price>
   596826
  </price>
  <rating>
   4.01
  </rating>
  <reviews>
   849780
  </reviews>
  <exclusive>
   yes
  </exclusive>
  <sporty>
   no
  </sporty>
 </clothing>
 <clothing>
  <id>
   493823799
  </id>
  <name>
   DC Belts V-3636
  </name>
  <category>
   Belts
  </category>
  <size>
   M
  </size>
  <color>
   Голубой
  </color>
  <material>
   Хлопок
  </material>
  <price>
   286493
  </price>
  <rating>
   2.39
  </rating>
  <reviews>
   369263
  </reviews>
  <sporty>
   yes
  </sporty>
 </clothing>
 <clothing>
  <id>
   531901731
  </id>
  <name>
   Fila Belts Y-2687
  </name>
  <category>
   Belts
  </category>
  <size>
   XXL
  </size>
  <color>
   Голубой
  </color>
  <material>
   Лен
  </material>
  <price>
   933245
  </price>
  <rating>
   1.05
  </rating>
  <reviews>
   893028
  </reviews>
  <sporty>
   no
  </sporty>
 </clothing>
 <clothing>
  <id>
   412804581
  </id>
  <name>
   Vans Belts Q-2515
  </name>
  <category>
   Belts
  </category>
  <size>
   M
  </size>
  <color>
   Зеленый
  </color>
  <material>
   Шелк
  </material>
  <price>
   128517
  </price>
  <rating>
   3.61
  </rating>
  <reviews>
   627550
  </reviews>
  <new>
   -
  </new>
  <sporty>
   no
  </sporty>
 </clothing>
 <clothing>
  <id>
   219849368
  </id>
  <name>
   DC Pants R-2618
  </name>
  <category>
   Pants
  </category>
  <size>
   XL
  </size>
  <color>
   Зеленый
  </color>
  <material>
   Полиэстер
  </material>
  <price>
   312629
  </price>
  <rating>
   3.46
  </rating>
  <reviews>
   411309
  </reviews>
  <new>
   -
  </new>
  <sporty>
   yes
  </sporty>
 </clothing>
 <clothing>
  <id>
   293991341
  </id>
  <name>
   Ellesse Skirt M-3755
  </name>
  <category>
   Skirt
  </category>
  <size>
   L
  </size>
  <color>
   Оранжевый
  </color>
  <material>
   Шерсть
  </material>
  <price>
   173703
  </price>
  <rating>
   4.34
  </rating>
  <reviews>
   316395
  </reviews>
  <new>
   -
  </new>
  <exclusive>
   yes
  </exclusive>
  <sporty>
   yes
  </sporty>
 </clothing>
 <clothing>
  <id>
   917672252
  </id>
  <name>
   DC Umbrellas E-6737
  </name>
  <category>
   Umbrellas
  </category>
  <size>
   S
  </size>
  <color>
   Оранжевый
  </color>
  <material>
   Шелк
  </material>
  <price>
   418318
  </price>
  <rating>
   1.76
  </rating>
  <reviews>
   336955
  </reviews>
  <sporty>
   no
  </sporty>
 </clothing>
 <clothing>
  <id>
   459571873
  </id>
  <name>
   Brooks Sweater X-1780
  </name>
  <category>
   Sweater
  </category>
  <size>
   M
  </size>
  <color>
   Желтый
  </color>
  <material>
   Вискоза
  </material>
  <price>
   901538
  </price>
  <rating>
   3.62
  </rating>
  <reviews>
   893486
  </reviews>
  <new>
   -
  </new>
  <exclusive>
   yes
  </exclusive>
 </clothing>
 <clothing>
  <id>
   145732426
  </id>
  <name>
   Brooks Dress V-2660
  </name>
  <category>
   Dress
  </category>
  <size>
   XL
  </size>
  <color>
   Голубой
  </color>
  <material>
   Вискоза
  </material>
  <price>
   113958
  </price>
  <rating>
   2.94
  </rating>
  <reviews>
   896229
  </reviews>
  <new>
   -
  </new>
  <sporty>
   yes
  </sporty>
 </clothing>
 <clothing>
  <id>
   351870895
  </id>
  <name>
   Vans T-shirt C-9412
  </name>
  <category>
   T-shirt
  </category>
  <size>
   S
  </size>
  <color>
   Желтый
  </color>
  <material>
   Лен
  </material>
  <price>
   794063
  </price>
  <rating>
   4.51
  </rating>
  <reviews>
   318889
  </reviews>
  <sporty>
   no
  </sporty>
 </clothing>
 <clothing>
  <id>
   827010271
  </id>
  <name>
   Fila Shirt H-8760
  </name>
  <category>
   Shirt
  </category>
  <size>
   XL
  </size>
  <color>
   Желтый
  </color>
  <material>
   Шелк
  </material>
  <price>
   977597
  </price>
  <rating>
   4.28
  </rating>
  <reviews>
   688901
  </reviews>
  <exclusive>
   yes
  </exclusive>
  <sporty>
   no
  </sporty>
 </clothing>
 <clothing>
  <id>
   889785664
  </id>
  <name>
   Fila Handbags K-2044
  </name>
  <category>
   Handbags
  </category>
  <size>
   M
  </size>
  <color>
   Зеленый
  </color>
  <material>
   Нейлон
  </material>
  <price>
   338350
  </price>
  <rating>
   4.94
  </rating>
  <reviews>
   467789
  </reviews>
  <sporty>
   no
  </sporty>
 </clothing>
 <clothing>
  <id>
   217253866
  </id>
  <name>
   Asics Sweater V-2979
  </name>
  <category>
   Sweater
  </category>
  <size>
   S
  </size>
  <color>
   Синий
  </color>
  <material>
   Кожа
  </material>
  <price>
   748292
  </price>
  <rating>
   4.92
  </rating>
  <reviews>
   266071
  </reviews>
  <new>
   +
  </new>
 </clothing>
 <clothing>
  <id>
   458367084
  </id>
  <name>
   Converse Jeans J-2051
  </name>
  <category>
   Jeans
  </category>
  <size>
   L
  </size>
  <color>
   Оранжевый
  </color>
  <material>
   Шерсть
  </material>
  <price>
   327583
  </price>
  <rating>
   1.22
  </rating>
  <reviews>
   854443
  </reviews>
  <new>
   -
  </new>
  <sporty>
   yes
  </sporty>
 </clothing>
 <clothing>
  <id>
   497317096
  </id>
  <name>
   Puma Pants H-1022
  </name>
  <category>
   Pants
  </category>
  <size>
   S
  </size>
  <color>
   Зеленый
  </color>
  <material>
   Нейлон
  </material>
  <price>
   128690
  </price>
  <rating>
   4.25
  </rating>
  <reviews>
   48328
  </reviews>
  <new>
   -
  </new>
  <exclusive>
   yes
  </exclusive>
  <sporty>
   yes
  </sporty>
 </clothing>
 <clothing>
  <id>
   315525320
  </id>
  <name>
   New Balance Sweater G-3136
  </name>
  <category>
   Sweater
  </category>
  <size>
   S
  </size>
  <color>
   Оранжевый
  </color>
  <material>
   Полиэстер
  </material>
  <price>
   805685
  </price>
  <rating>
   3.47
  </rating>
  <reviews>
   775462
  </reviews>
  <new>
   -
  </new>
  <exclusive>
   yes
  </exclusive>
 </clothing>
 <clothing>
  <id>
   197816528
  </id>
  <name>
   Adidas Gloves E-3524
  </name>
  <category>
   Gloves
  </category>
  <size>
   XL
  </size>
  <color>
   Зеленый
  </color>
  <material>
   Шерсть
  </material>
  <price>
   694356
  </price>
  <rating>
   3.51
  </rating>
  <reviews>
   237033
  </reviews>
  <exclusive>
   no
  </exclusive>
 </clothing>
 <clothing>
  <id>
   479149894
  </id>
  <name>
   PleinSport Hat G-7721
  </name>
  <category>
   Hat
  </category>
  <size>
   S
  </size>
  <color>
   Фиолетовый
  </color>
  <material>
   Полиэстер
  </material>
  <price>
   828695
  </price>
  <rating>
   2.68
  </rating>
  <reviews>
   441489
  </reviews>
  <new>
   -
  </new>
  <exclusive>
   no
  </exclusive>
 </clothing>
 <clothing>
  <id>
   235530448
  </id>
  <name>
   Under Armour Umbrellas D-6821
  </name>
  <category>
   Umbrellas
  </category>
  <size>
   L
  </size>
  <color>
   Желтый
  </color>
  <material>
   Шерсть
  </material>
  <price>
   557442
  </price>
  <rating>
   3.25
  </rating>
  <reviews>
   753730
  </reviews>
  <sporty>
   yes
  </sporty>
 </clothing>
</clothing-items>
